securefabric/__init__.py
securefabric/client.py
securefabric/securefabric_pb2.py
securefabric/securefabric_pb2.pyi
securefabric/securefabric_pb2_grpc.py
securefabric_client-0.1.0.dist-info/METADATA
securefabric_client-0.1.0.dist-info/WHEEL
securefabric_client-0.1.0.dist-info/licenses/LICENSE
securefabric_client-0.1.0.dist-info/RECORD
