Metadata-Version: 2.4
Name: securefabric-client
Version: 0.1.0
Summary: Official Python client SDK for SecureFabric - secure, low-latency messaging fabric
Project-URL: Homepage, https://secure-fabric.io
Project-URL: Documentation, https://secure-fabric.io/docs
Project-URL: Repository, https://github.com/NodeCube/securefabric-public
Project-URL: Issues, https://github.com/NodeCube/securefabric-public/issues
Project-URL: Changelog, https://github.com/NodeCube/securefabric-public/blob/main/CHANGELOG.md
Author-email: "NodeCube d.o.o." <contact@secure-fabric.io>
License-Expression: Apache-2.0
License-File: LICENSE
Keywords: fabric,grpc,messaging,secure,securefabric
Classifier: Development Status :: 4 - Beta
Classifier: Intended Audience :: Developers
Classifier: License :: OSI Approved :: Apache Software License
Classifier: Operating System :: OS Independent
Classifier: Programming Language :: Python :: 3
Classifier: Programming Language :: Python :: 3 :: Only
Classifier: Programming Language :: Python :: 3.8
Classifier: Programming Language :: Python :: 3.9
Classifier: Programming Language :: Python :: 3.10
Classifier: Programming Language :: Python :: 3.11
Classifier: Programming Language :: Python :: 3.12
Classifier: Topic :: Software Development :: Libraries :: Python Modules
Classifier: Topic :: System :: Networking
Classifier: Typing :: Typed
Requires-Python: >=3.8
Requires-Dist: cryptography>=41.0.0
Requires-Dist: grpcio>=1.54.0
Requires-Dist: protobuf>=4.21.0
Provides-Extra: dev
Requires-Dist: black>=23.0.0; extra == 'dev'
Requires-Dist: grpcio-tools>=1.54.0; extra == 'dev'
Requires-Dist: mypy>=1.0.0; extra == 'dev'
Requires-Dist: pytest-asyncio>=0.21.0; extra == 'dev'
Requires-Dist: pytest>=7.0.0; extra == 'dev'
Requires-Dist: requests>=2.28.0; extra == 'dev'
Requires-Dist: types-grpcio; extra == 'dev'
Requires-Dist: types-protobuf>=4.21.0; extra == 'dev'
